{
  "links": [
    {
      "id": 1,
      "category": "行政",
      "title": "學生圖表",
      "url": "https://dfleoyang-hlhs.github.io/HL-STUDENT/"
    },
    {
      "id": 2,
      "category": "行政",
      "title": "115學測分析",
      "url": "https://dfleoyang-hlhs.github.io/gsat-hlhs-115/"
    },
    {
      "id": 3,
      "category": "行政",
      "title": "115大學個人申請(2026)",
      "url": "https://dfleoyang-hlhs.github.io/CACHLHS115/"
    },
    {
      "id": 4,
      "category": "行政",
      "title": "課表查詢",
      "url": "https://dfleoyang-hlhs.github.io/hlhs_class/"
    },
    {
      "id": 5,
      "category": "教學",
      "title": "當下的力量",
      "url": "https://dfleoyang-hlhs.github.io/powernow/"
    },
    {
      "id": 6,
      "category": "教學",
      "title": "化學元素",
      "url": "https://dfleoyang-hlhs.github.io/chemicalelement/"
    },
    {
      "id": 7,
      "category": "教學",
      "title": "高中化學",
      "url": "https://dfleoyang-hlhs.github.io/chem_master/"
    },
    {
      "id": 8,
      "category": "教學",
      "title": "里歐咖啡",
      "url": "https://dfleoyang-hlhs.github.io/leocafe/"
    }
  ],
  "nextId": 9
}